SyncAlgo/DataSync.py
SyncAlgo/DataTraining.py
SyncAlgo/__init__.py
SyncAlgo/example_run.py
SyncAlgo/functions.py
SyncAlgo/utils.py
SyncAlgo/utils_function.py
SyncAlgo-0.1.2.dist-info/LICENSE
SyncAlgo-0.1.2.dist-info/METADATA
SyncAlgo-0.1.2.dist-info/WHEEL
SyncAlgo-0.1.2.dist-info/top_level.txt
SyncAlgo-0.1.2.dist-info/RECORD
