Metadata-Version: 2.1
Name: SyncAlgo
Version: 0.1.2
Summary: Example package for sync
Author-email: Weiwen Zhao <ywr1774@gmail.com>
License: Copyright (c) 2018 The Python Packaging Authority        
Project-URL: Homepage, https://github.com/KKiriri/Sync-Package
Project-URL: Bug Tracker, https://github.com/KKiriri/Sync-Package/issues
Classifier: Programming Language :: Python :: 3
Classifier: License :: OSI Approved :: MIT License
Classifier: Operating System :: OS Independent
Requires-Python: <3.9,>=3.5
License-File: LICENSE
Requires-Dist: dask[dataframe] (~=2.30.0)
Requires-Dist: numpy (~=1.19.5)
Requires-Dist: pandas (~=1.3.3)
Requires-Dist: scikit-learn (~=1.0.2)
Requires-Dist: scipy (~=1.5.4)
Requires-Dist: tensorflow (~=2.5.0)
